MANIFEST.in
README.rst
setup.cfg
setup.py
docs/Makefile
docs/api.rst
docs/conf.py
docs/index.rst
docs/installation.rst
docs/make.bat
docs/usage.rst
docs/api/time_execution.backends.rst
docs/api/time_execution.rst
py_timeexecution.egg-info/PKG-INFO
py_timeexecution.egg-info/SOURCES.txt
py_timeexecution.egg-info/dependency_links.txt
py_timeexecution.egg-info/not-zip-safe
py_timeexecution.egg-info/requires.txt
py_timeexecution.egg-info/top_level.txt
requirements/requirements-base.txt
requirements/requirements-testing.txt
tests/__init__.py
tests/conftest.py
tests/test_base_backend.py
tests/test_elasticsearch.py
tests/test_fqn.py
tests/test_hooks.py
tests/test_influxdb.py
time_execution/__init__.py
time_execution/time_execution.py
time_execution/backends/__init__.py
time_execution/backends/base.py
time_execution/backends/elasticsearch.py
time_execution/backends/influxdb.py